Verilog/verilog_positive_edge_detector/pos_edge_det_module.v
module pos_edge_det (
    input clk,
    input sig,
    output pe
);

    //Khối lưu trữ giá trị trước đó của sig bằng cách dùng reg và flipflop
    reg sig_dly;
    always @(posedge clk) begin
        sig_dly <= sig;
    end

    //Phép tổng hợp logic cho pe (sig tích cực lên thì pe = 1)
    assign pe = sig & ~sig_dly;

endmodule

Verilog/verilog_positive_edge_detector/pos_edge_det_tb.v
// Code your testbench here
// or browse Examples
module tb;
	reg sig;                                  // Declare internal TB signal called sig to drive the sig pin of the design
	reg clk;                                  // Declare internal TB signal called clk to drive clock to the design
	
	// Instantiate the design in TB and connect with signals in TB
	pos_edge_det ped0 (  .sig(sig),           
    					 .clk(clk),
 			      		 .pe(pe));

	// Generate a clock of 100MHz
	always #5 clk = ~clk;           
	
	// Drive stimulus to the design
	initial begin
		clk <= 0;
		sig <= 0;
		#15 sig <= 1;
		#20 sig <= 0;
		#15 sig <= 1;
		#10 sig <= 0;
		#20 $finish;
	end	
  
  	initial begin
      	$dumpvars;
      $dumpfile("dump.vcd");
    end
    
endmodule

Verilog/verilog_positive_edge_detector/dump.vcd
$date
	Mon Sep 28 16:11:15 2026
$end
$version
	Icarus Verilog
$end
$timescale
	1s
$end
$scope module tb $end
$var wire 1 ! pe $end
$var reg 1 " clk $end
$var reg 1 # sig $end
$scope module ped0 $end
$var wire 1 " clk $end
$var wire 1 ! pe $end
$var wire 1 # sig $end
$var reg 1 $ sig_dly $end
$upscope $end
$upscope $end
$enddefinitions $end
#0
$dumpvars
x$
0#
0"
0!
$end
#5
0$
1"
#10
0"
#15
1!
1#
1"
#20
0"
#25
0!
1$
1"
#30
0"
#35
0#
1"
#40
0"
#45
0$
1"
#50
1!
1#
0"
#55
0!
1$
1"
#60
0#
0"
#65
0$
1"
