Verilog/verilog_sequence_detector/sequence_detector_module.v
module det_1011 (
    input clk,
    input rstn,
    input in,
    output out
);

    localparam[2:0] IDLE = 0,
                    S1   = 1,
                    S10  = 2,
                    S101 = 3,
                    S1011= 4;

    reg[2:0] cur_state, next_state;

    //Khối lưu trữ trạng thái
    always @(posedge clk) begin
        if(!rstn) 
            cur_state <= IDLE;
        else
            cur_state <= next_state;
    end

    //Khối tính toán trạng thái tiếp theo
    always @(*) begin
        case(cur_state)
            IDLE : begin
                if(in) next_state = S1;
                else next_state = IDLE;
            end

            S1 : begin
                if(in) next_state = S1;
                else next_state = S10;
            end

            S10 : begin
                if(in) next_state = S101;
                else next_state = IDLE;
            end

            S101 : begin
                if(in) next_state = S1011;
                else next_state = S10;
            end

            S1011 : begin
                if(in) next_state = S1;
                else next_state = S10;
            end

            default : next_state = IDLE;
        endcase
    end

    //Phép tổ hợp cho output (output = 1 khi state = S1011)
    assign out = (cur_state == S1011);

endmodule

Verilog/verilog_sequence_detector/sequence_detector_tb.v
`timescale 1ns/1ps

module tb;
  // 1. Khai báo tín hiệu kết nối
  reg        clk;
  reg        in;
  reg        rstn;
  wire       out;

  // Biến phục vụ stimulus
  reg [1:0]  l_dly;
  reg        tb_in;
  integer    loop = 20; // Tăng số lần lặp ngẫu nhiên để test bao phủ
  integer    i;         // Khai báo biến đếm chuẩn Verilog

  // 2. Tạo xung nhịp 50MHz (Chu kỳ T = 20ns)
  initial clk = 0;      // Khởi tạo mức 0 tuyệt đối tại t=0
  always #10 clk = ~clk;

  // 3. Kết nối DUT (Device Under Test)
  det_1011 u0 (
    .clk  (clk),
    .rstn (rstn),
    .in   (in),
    .out  (out)
  );

  // 4. Khối điều khiển kích thích (Stimulus Process)
  initial begin
    // Cấu hình xuất file sóng xem trên GTKWave
    $dumpfile("seq_det_output.vcd");
    $dumpvars(0, tb);   // Dump toàn bộ tín hiệu từ module đỉnh tb trở xuống

    // Khởi tạo các tín hiệu đầu vào ban đầu
    rstn = 0;
    in   = 0;

    // Giữ reset tích cực mức thấp trong 5 chu kỳ xung nhịp
    repeat (5) @(posedge clk);
    rstn <= 1;          // Nhả reset

    // ----------------------------------------------------
    // Kịch bản 1: Directed Pattern (Kịch bản định hướng sẵn)
    // Mục tiêu kiểm tra chuỗi: 1-0-1-1 rồi lặp lại 1-0-1-1
    // ----------------------------------------------------
    @(posedge clk) in <= 1;
    @(posedge clk) in <= 0;
    @(posedge clk) in <= 1;
    @(posedge clk) in <= 1; // Khớp chuỗi lần 1 -> out bật lên 1
    @(posedge clk) in <= 0;
    @(posedge clk) in <= 0;
    @(posedge clk) in <= 1;
    @(posedge clk) in <= 1;
    @(posedge clk) in <= 0;
    @(posedge clk) in <= 1;
    @(posedge clk) in <= 1; // Khớp chuỗi lần 2 -> out bật lên 1

    // ----------------------------------------------------
    // Kịch bản 2: Random Stimulus (Kích thích ngẫu nhiên)
    // ----------------------------------------------------
    for (i = 0; i < loop; i = i + 1) begin
      l_dly = $random;
      repeat (l_dly) @(posedge clk);
      tb_in = $random;
      in <= tb_in;
    end

    // Đợi thêm một khoảng thời gian để quan sát hết chu kỳ cuối
    #100;
    $display(">> Hoan thanh mo phong kiem tra FSM 1011 <<");
    $finish;
  end

  // 5. In log tự động ra Terminal để kiểm tra nhanh kết quả
  always @(posedge clk) begin
    if (out) begin
      $display("[THOI GIAN %0t ns] DETECTED: Phat hien chuoi 1011 hop le!", $time);
    end
  end

endmodule

Verilog/verilog_sequence_detector/seq_det_output.vcd
$date
	Mon Sep 28 11:44:11 2026
$end
$version
	Icarus Verilog
$end
$timescale
	1s
$end
$scope module tb $end
$var wire 1 ! out $end
$var reg 1 " clk $end
$var reg 1 # in $end
$var reg 2 $ l_dly [1:0] $end
$var reg 1 % rstn $end
$var reg 1 & tb_in $end
$var integer 32 ' loop [31:0] $end
$scope module u0 $end
$var wire 1 " clk $end
$var wire 1 # in $end
$var wire 1 % rstn $end
$var wire 1 ! out $end
$var reg 3 ( cur_state [2:0] $end
$var reg 3 ) next_state [2:0] $end
$upscope $end
$scope begin $ivl_for_loop0 $end
$var integer 32 * i [31:0] $end
$upscope $end
$upscope $end
$enddefinitions $end
#0
$dumpvars
bx *
bx )
bx (
b1 '
x&
0%
bx $
0#
0"
x!
$end
#10
b0 )
0!
b0 (
1"
#20
0"
#30
1"
#40
0"
#50
1"
#60
0"
#70
1"
#80
0"
#90
1%
1"
#100
0"
#110
b1 )
1#
1"
#120
0"
#130
b10 )
b1 (
0#
1"
#140
0"
#150
b11 )
1#
b10 (
1"
#160
0"
#170
b100 )
b11 (
1"
#180
0"
#190
b0 )
0#
1!
b100 (
1"
#200
0"
#210
0!
b0 (
1"
#220
0"
#230
b1 )
1#
1"
#240
0"
#250
b0 )
b1 (
1"
#260
0"
#270
0#
b0 (
1"
#280
0"
#290
b1 )
1#
1"
#300
0"
#310
b0 )
b1 (
1&
b0 $
b1 *
1"
#320
0"
#330
b1 )
b0 (
1"
#340
0"
#350
b0 )
b1 (
1"
#360
0"
#370
b1 )
b0 (
1"
#380
0"
#390
b0 )
b1 (
1"
#400
0"
#410
b1 )
b0 (
1"
