Verilog/verilog_pattern_detector/pat_dec_module.v
module det_110101 (
    input clk,
    input rstn,
    input in,
    output out
);

    parameter IDLE    = 0,
              S1      = 1,
              S11     = 2,
              S110    = 3,
              S1101   = 4,
              S11010  = 5,
              S110101 = 6;

    reg[2:0] cur_state, next_state;

    //Khối xử lí trạng thái tiếp theo
    always @(*) begin
        case(cur_state) 
            IDLE : begin
                if(in) next_state = S1;
                else next_state = IDLE;
            end

            S1 : begin
                if(in) next_state = S11;
                else next_state = IDLE;
            end

            S11 : begin
                if(in) next_state = S11;
                else next_state = S110;
            end

            S110 : begin
                if(in) next_state = S1101;
                else next_state = IDLE;
            end

            S1101 : begin
                if(in) next_state = S11;
                else next_state = S11010;
            end

            S11010 : begin
                if(in) next_state = S110101;
                else next_state = IDLE;
            end

            S110101 : begin
                if(in) next_state = S11;
                else next_state = IDLE;
            end

            default : next_state = IDLE;
        endcase
    end
    
    //Khối lưu trữ và xử lí trạng thái tiếp theo
    always @(posedge clk) begin
        if(!rstn)
            cur_state = IDLE;
        else
            cur_state = next_state;
    end

    //Phép tổ hợp tính toán cho output (110101 thì out = 1)
    assign out = (cur_state == 6);

endmodule

Verilog/verilog_pattern_detector/pat_dec_tb.v
module tb;
  reg clk, in, rstn;
  wire out;
  integer l_dly;
  
  always #10 clk = ~clk;
  
  det_110101 u0 ( .clk(clk), .rstn(rstn), .in(in), .out(out) );
  
  initial begin
  	clk <= 0;
    rstn <= 0;
    in <= 0;
    
    repeat (5) @ (posedge clk);
    rstn <= 1;

    @(posedge clk) in <= 1;
    @(posedge clk) in <= 1;
    @(posedge clk) in <= 0;
    @(posedge clk) in <= 1;
    @(posedge clk) in <= 0;
    @(posedge clk) in <= 1;
    @(posedge clk) in <= 1;
    @(posedge clk) in <= 1;
    @(posedge clk) in <= 0;
    @(posedge clk) in <= 1;
    @(posedge clk) in <= 0;
    @(posedge clk) in <= 1;
    
    #100 $finish;
  end
  
  always @ (posedge clk) begin
    $strobe("T=%0t in=%0b out=%0b", $time, in, out);
  end
  
  initial begin
    $dumpvars;
    $dumpfile("dump.vcd");
  end
  
endmodule

Verilog/verilog_pattern_detector/dump.vcd
$date
	Mon Sep 28 15:56:28 2026
$end
$version
	Icarus Verilog
$end
$timescale
	1s
$end
$scope module tb $end
$var wire 1 ! out $end
$var reg 1 " clk $end
$var reg 1 # in $end
$var reg 1 $ rstn $end
$scope module u0 $end
$var wire 1 " clk $end
$var wire 1 # in $end
$var wire 1 $ rstn $end
$var wire 1 ! out $end
$var reg 3 % cur_state [2:0] $end
$var reg 3 & next_state [2:0] $end
$upscope $end
$upscope $end
$enddefinitions $end
#0
$dumpvars
b0 &
bx %
0$
0#
0"
x!
$end
#10
0!
b0 %
1"
#20
0"
#30
1"
#40
0"
#50
1"
#60
0"
#70
1"
#80
0"
#90
1$
1"
#100
0"
#110
b1 &
1#
1"
#120
0"
#130
b10 &
b1 %
1"
#140
0"
#150
b11 &
0#
b10 %
1"
#160
0"
#170
1#
b100 &
b11 %
1"
#180
0"
#190
0#
b101 &
b100 %
1"
#200
0"
#210
1#
b110 &
b101 %
1"
#220
0"
#230
b10 &
1!
b110 %
1"
#240
0"
#250
0!
b10 %
1"
#260
0"
#270
b11 &
0#
1"
#280
0"
#290
1#
b100 &
b11 %
1"
#300
0"
#310
0#
b101 &
b100 %
1"
#320
0"
#330
1#
b110 &
b101 %
1"
#340
0"
#350
b10 &
1!
b110 %
1"
#360
0"
#370
0!
b10 %
1"
